{
  "nodes": {
    "SitePage /dev-404-page/": {
      "layout": "index",
      "jsonName": "dev-404-page.json",
      "internalComponentName": "ComponentDev404Page",
      "path": "/dev-404-page/",
      "component": "D:/temp/tutorial-part-four/.cache/dev-404-page.js",
      "componentChunkName": "component---cache-dev-404-page-js",
      "context": {},
      "pluginCreator___NODE": "Plugin dev-404-page",
      "pluginCreatorId": "Plugin dev-404-page",
      "componentPath": "D:/temp/tutorial-part-four/.cache/dev-404-page.js",
      "id": "SitePage /dev-404-page/",
      "parent": "SOURCE",
      "children": [],
      "internal": {
        "type": "SitePage",
        "contentDigest": "adff4e59ce8de76da9418fd0fbb6584d",
        "description": "Plugin dev-404-page",
        "owner": "internal-data-bridge"
      }
    },
    "Plugin dev-404-page": {
      "resolve": "D:/temp/tutorial-part-four/node_modules/gatsby/dist/internal-plugins/dev-404-page",
      "id": "Plugin dev-404-page",
      "name": "dev-404-page",
      "version": "1.0.0",
      "pluginOptions": {
        "plugins": []
      },
      "nodeAPIs": [
        "createPagesStatefully"
      ],
      "browserAPIs": [],
      "ssrAPIs": [],
      "pluginFilepath": "D:/temp/tutorial-part-four/node_modules/gatsby/dist/internal-plugins/dev-404-page",
      "packageJson": {
        "name": "dev-404-page",
        "description": "Internal plugin to add a 404 page in development with helpful information",
        "version": "1.0.0",
        "main": "index.js",
        "author": "Kyle Mathews <mathews.kyle@gmail.com>",
        "license": "MIT",
        "dependencies": [],
        "devDependencies": [],
        "peerDependencies": [],
        "optionalDependecies": [],
        "bundledDependecies": []
      },
      "parent": "SOURCE",
      "children": [],
      "internal": {
        "contentDigest": "967c6017d40314dfdf4e0808285c8160",
        "type": "SitePlugin",
        "owner": "internal-data-bridge"
      }
    },
    "Plugin component-page-creator": {
      "resolve": "D:/temp/tutorial-part-four/node_modules/gatsby/dist/internal-plugins/component-page-creator",
      "id": "Plugin component-page-creator",
      "name": "component-page-creator",
      "version": "1.0.0",
      "pluginOptions": {
        "plugins": []
      },
      "nodeAPIs": [
        "createPagesStatefully"
      ],
      "browserAPIs": [],
      "ssrAPIs": [],
      "pluginFilepath": "D:/temp/tutorial-part-four/node_modules/gatsby/dist/internal-plugins/component-page-creator",
      "packageJson": {
        "name": "component-page-creator",
        "description": "An internal Gatsby plugin that creates pages from component files in src/pages",
        "version": "1.0.0",
        "main": "index.js",
        "keywords": [
          "gatsby",
          "gatsby-plugin"
        ],
        "author": "Kyle Mathews <mathews.kyle@gmail.com>",
        "license": "MIT",
        "dependencies": [],
        "devDependencies": [],
        "peerDependencies": [],
        "optionalDependecies": [],
        "bundledDependecies": []
      },
      "parent": "SOURCE",
      "children": [],
      "internal": {
        "contentDigest": "877b90bfbe5580041aa3333e97ab2acc",
        "type": "SitePlugin",
        "owner": "internal-data-bridge"
      }
    },
    "Plugin component-layout-creator": {
      "resolve": "D:/temp/tutorial-part-four/node_modules/gatsby/dist/internal-plugins/component-layout-creator",
      "id": "Plugin component-layout-creator",
      "name": "component-layout-creator",
      "version": "1.0.0",
      "pluginOptions": {
        "plugins": []
      },
      "nodeAPIs": [
        "createLayouts"
      ],
      "browserAPIs": [],
      "ssrAPIs": [],
      "pluginFilepath": "D:/temp/tutorial-part-four/node_modules/gatsby/dist/internal-plugins/component-layout-creator",
      "packageJson": {
        "name": "component-layout-creator",
        "description": "An internal Gatsby plugin that creates pages from component files in src/layouts",
        "version": "1.0.0",
        "main": "index.js",
        "keywords": [
          "gatsby",
          "gatsby-plugin"
        ],
        "author": "Kyle Mathews <mathews.kyle@gmail.com>",
        "license": "MIT",
        "dependencies": [],
        "devDependencies": [],
        "peerDependencies": [],
        "optionalDependecies": [],
        "bundledDependecies": []
      },
      "parent": "SOURCE",
      "children": [],
      "internal": {
        "contentDigest": "c61bab7a37e63a7c1c6287a18adca669",
        "type": "SitePlugin",
        "owner": "internal-data-bridge"
      }
    },
    "Plugin internal-data-bridge": {
      "resolve": "D:/temp/tutorial-part-four/node_modules/gatsby/dist/internal-plugins/internal-data-bridge",
      "id": "Plugin internal-data-bridge",
      "name": "internal-data-bridge",
      "version": "1.0.0",
      "pluginOptions": {
        "plugins": []
      },
      "nodeAPIs": [
        "sourceNodes",
        "onCreatePage"
      ],
      "browserAPIs": [],
      "ssrAPIs": [],
      "pluginFilepath": "D:/temp/tutorial-part-four/node_modules/gatsby/dist/internal-plugins/internal-data-bridge",
      "packageJson": {
        "name": "internal-data-bridge",
        "description": "An internal Gatsby plugin which creates data nodes from internal data",
        "version": "1.0.0",
        "main": "index.js",
        "author": "Kyle Mathews <mathews.kyle@gmail.com>",
        "license": "MIT",
        "dependencies": [],
        "devDependencies": [],
        "peerDependencies": [],
        "optionalDependecies": [],
        "bundledDependecies": []
      },
      "parent": "SOURCE",
      "children": [],
      "internal": {
        "contentDigest": "e0ff4e6e75e8986c1314b8a205888ff8",
        "type": "SitePlugin",
        "owner": "internal-data-bridge"
      }
    },
    "Plugin prod-404": {
      "resolve": "D:/temp/tutorial-part-four/node_modules/gatsby/dist/internal-plugins/prod-404",
      "id": "Plugin prod-404",
      "name": "prod-404",
      "version": "1.0.0",
      "pluginOptions": {
        "plugins": []
      },
      "nodeAPIs": [
        "onCreatePage"
      ],
      "browserAPIs": [],
      "ssrAPIs": [],
      "pluginFilepath": "D:/temp/tutorial-part-four/node_modules/gatsby/dist/internal-plugins/prod-404",
      "packageJson": {
        "name": "prod-404",
        "description": "Internal plugin to detect various flavors of 404 pages and ensure there's a 404.html path created as well to ensure compatability with static hosts",
        "version": "1.0.0",
        "main": "index.js",
        "author": "Kyle Mathews <mathews.kyle@gmail.com>",
        "license": "MIT",
        "dependencies": [],
        "devDependencies": [],
        "peerDependencies": [],
        "optionalDependecies": [],
        "bundledDependecies": []
      },
      "parent": "SOURCE",
      "children": [],
      "internal": {
        "contentDigest": "70df9b9fb386c38e9c63342f6b05f68f",
        "type": "SitePlugin",
        "owner": "internal-data-bridge"
      }
    },
    "Plugin query-runner": {
      "resolve": "D:/temp/tutorial-part-four/node_modules/gatsby/dist/internal-plugins/query-runner",
      "id": "Plugin query-runner",
      "name": "query-runner",
      "version": "1.0.0",
      "pluginOptions": {
        "plugins": []
      },
      "nodeAPIs": [
        "onCreatePage",
        "onCreateLayout"
      ],
      "browserAPIs": [],
      "ssrAPIs": [],
      "pluginFilepath": "D:/temp/tutorial-part-four/node_modules/gatsby/dist/internal-plugins/query-runner",
      "packageJson": {
        "name": "query-runner",
        "description": "Internal plugin for running queries",
        "version": "1.0.0",
        "main": "index.js",
        "author": "",
        "license": "MIT",
        "dependencies": [],
        "devDependencies": [],
        "peerDependencies": [],
        "optionalDependecies": [],
        "bundledDependecies": []
      },
      "parent": "SOURCE",
      "children": [],
      "internal": {
        "contentDigest": "c7947eed72bdd35f863dd32f85e6a571",
        "type": "SitePlugin",
        "owner": "internal-data-bridge"
      }
    },
    "Plugin gatsby-plugin-glamor": {
      "resolve": "D:/temp/tutorial-part-four/node_modules/gatsby-plugin-glamor",
      "id": "Plugin gatsby-plugin-glamor",
      "name": "gatsby-plugin-glamor",
      "version": "1.6.13",
      "pluginOptions": {
        "plugins": []
      },
      "nodeAPIs": [
        "modifyWebpackConfig",
        "modifyBabelrc"
      ],
      "browserAPIs": [
        "onClientEntry"
      ],
      "ssrAPIs": [
        "replaceRenderer"
      ],
      "pluginFilepath": "D:/temp/tutorial-part-four/node_modules/gatsby-plugin-glamor",
      "packageJson": {
        "name": "gatsby-plugin-glamor",
        "description": "Gatsby plugin to add support for Glamor",
        "version": "1.6.13",
        "main": "index.js",
        "keywords": [
          "gatsby",
          "gatsby-plugin",
          "glamor"
        ],
        "author": {
          "name": "Kyle Mathews",
          "email": "mathews.kyle@gmail.com"
        },
        "license": "MIT",
        "dependencies": [
          {
            "name": "babel-runtime",
            "version": "^6.26.0"
          },
          {
            "name": "glamor",
            "version": "^2.20.29"
          }
        ],
        "devDependencies": [
          {
            "name": "babel-cli",
            "version": "^6.26.0"
          },
          {
            "name": "cross-env",
            "version": "^5.0.5"
          }
        ],
        "peerDependencies": [
          {
            "name": "gatsby",
            "version": "^1.0.0"
          }
        ],
        "optionalDependecies": [],
        "bundledDependecies": []
      },
      "parent": "SOURCE",
      "children": [],
      "internal": {
        "contentDigest": "2940123f145189588551b20ad452b448",
        "type": "SitePlugin",
        "owner": "internal-data-bridge"
      }
    },
    "Plugin gatsby-plugin-typography": {
      "resolve": "D:/temp/tutorial-part-four/node_modules/gatsby-plugin-typography",
      "id": "Plugin gatsby-plugin-typography",
      "name": "gatsby-plugin-typography",
      "version": "1.7.18",
      "pluginOptions": {
        "plugins": [],
        "pathToConfigModule": "src/utils/typography"
      },
      "nodeAPIs": [
        "onPreBootstrap"
      ],
      "browserAPIs": [
        "onClientEntry"
      ],
      "ssrAPIs": [
        "onRenderBody"
      ],
      "pluginFilepath": "D:/temp/tutorial-part-four/node_modules/gatsby-plugin-typography",
      "packageJson": {
        "name": "gatsby-plugin-typography",
        "description": "Gatsby plugin to setup server rendering of Typography.js' CSS",
        "version": "1.7.18",
        "main": "index.js",
        "keywords": [
          "gatsby",
          "gatsby-plugin",
          "typography",
          "typography.js"
        ],
        "author": {
          "name": "Kyle Mathews",
          "email": "mathews.kyle@gmail.com"
        },
        "license": "MIT",
        "dependencies": [
          {
            "name": "babel-runtime",
            "version": "^6.26.0"
          },
          {
            "name": "react-typography",
            "version": "^0.16.1"
          },
          {
            "name": "typography",
            "version": "^0.16.0"
          }
        ],
        "devDependencies": [
          {
            "name": "cross-env",
            "version": "^5.0.5"
          }
        ],
        "peerDependencies": [
          {
            "name": "gatsby",
            "version": "^1.0.0"
          }
        ],
        "optionalDependecies": [],
        "bundledDependecies": []
      },
      "parent": "SOURCE",
      "children": [],
      "internal": {
        "contentDigest": "e6e3a234e725046296a219c73591625b",
        "type": "SitePlugin",
        "owner": "internal-data-bridge"
      }
    },
    "Plugin default-site-plugin": {
      "resolve": "D:/temp/tutorial-part-four",
      "id": "Plugin default-site-plugin",
      "name": "default-site-plugin",
      "version": "5044a1b15ae0355798fec08b3fca52f3",
      "pluginOptions": {
        "plugins": []
      },
      "nodeAPIs": [],
      "browserAPIs": [],
      "ssrAPIs": [],
      "pluginFilepath": "D:/temp/tutorial-part-four",
      "packageJson": {
        "name": "gatsby-starter-hello-world",
        "description": "Gatsby hello world starter",
        "license": "MIT",
        "dependencies": [
          {
            "name": "gatsby",
            "version": "^1.9.250"
          },
          {
            "name": "gatsby-link",
            "version": "^1.6.40"
          },
          {
            "name": "gatsby-plugin-glamor",
            "version": "^1.6.13"
          },
          {
            "name": "gatsby-plugin-typography",
            "version": "^1.7.18"
          },
          {
            "name": "glamorous",
            "version": "^4.12.4"
          },
          {
            "name": "typography-theme-kirkham",
            "version": "^0.16.3"
          }
        ],
        "devDependencies": [],
        "peerDependencies": [],
        "optionalDependecies": [],
        "bundledDependecies": []
      },
      "parent": "SOURCE",
      "children": [],
      "internal": {
        "contentDigest": "df1cd863c9b7a1d4875d8d5ec050f740",
        "type": "SitePlugin",
        "owner": "internal-data-bridge"
      }
    },
    "Site": {
      "siteMetadata": {},
      "port": "8000",
      "host": "localhost",
      "pathPrefix": "",
      "polyfill": true,
      "buildTime": "2018-04-26T09:32:51.119Z",
      "id": "Site",
      "parent": "SOURCE",
      "children": [],
      "internal": {
        "contentDigest": "770418f4e41b058c04b6650e6dd7c95f",
        "type": "Site",
        "owner": "internal-data-bridge"
      }
    },
    "SitePage /about/": {
      "layout": "index",
      "jsonName": "about.json",
      "internalComponentName": "ComponentAbout",
      "path": "/about/",
      "component": "D:/temp/tutorial-part-four/src/pages/about.js",
      "componentChunkName": "component---src-pages-about-js",
      "context": {},
      "pluginCreator___NODE": "Plugin component-page-creator",
      "pluginCreatorId": "Plugin component-page-creator",
      "componentPath": "D:/temp/tutorial-part-four/src/pages/about.js",
      "id": "SitePage /about/",
      "parent": "SOURCE",
      "children": [],
      "internal": {
        "type": "SitePage",
        "contentDigest": "cc16e4c5eb8304fb855ddbdd9ef48a17",
        "description": "Plugin component-page-creator",
        "owner": "internal-data-bridge"
      }
    },
    "SitePage /": {
      "layout": "index",
      "jsonName": "index.json",
      "internalComponentName": "ComponentIndex",
      "path": "/",
      "component": "D:/temp/tutorial-part-four/src/pages/index.js",
      "componentChunkName": "component---src-pages-index-js",
      "context": {},
      "pluginCreator___NODE": "Plugin component-page-creator",
      "pluginCreatorId": "Plugin component-page-creator",
      "componentPath": "D:/temp/tutorial-part-four/src/pages/index.js",
      "id": "SitePage /",
      "parent": "SOURCE",
      "children": [],
      "internal": {
        "type": "SitePage",
        "contentDigest": "d3f0bd86214be447bfe7b649b70a132f",
        "description": "Plugin component-page-creator",
        "owner": "internal-data-bridge"
      }
    }
  },
  "status": {
    "plugins": {},
    "PLUGINS_HASH": "710fd906d8ed82dfd447127254188a61"
  },
  "componentDataDependencies": {
    "nodes": {},
    "connections": {
      "SitePage": [
        "/dev-404-page/"
      ]
    }
  }
}